celery_mongobeat/__init__.py
celery_mongobeat/beat.py
celery_mongobeat/helpers.py
celery_mongobeat-0.1.20.dist-info/licenses/LICENSE
celery_mongobeat-0.1.20.dist-info/METADATA
celery_mongobeat-0.1.20.dist-info/WHEEL
celery_mongobeat-0.1.20.dist-info/entry_points.txt
celery_mongobeat-0.1.20.dist-info/top_level.txt
celery_mongobeat-0.1.20.dist-info/RECORD
