Metadata-Version: 2.4
Name: celery-mongobeat
Version: 0.1.20
Summary: A Celery Beat scheduler that stores the schedule in MongoDB.
Author-email: William Thomas <52611686+sockmysox@users.noreply.github.com>
License:                                  Apache License
Project-URL: Homepage, https://github.com/sockmysox/celery-mongobeat
Project-URL: Bug Tracker, https://github.com/sockmysox/celery-mongobeat/issues
Keywords: celery,beat,scheduler,mongodb,mongo
Classifier: Development Status :: 4 - Beta
Classifier: Intended Audience :: Developers
Classifier: Topic :: Software Development :: Libraries :: Python Modules
Classifier: Programming Language :: Python :: 3
Classifier: Programming Language :: Python :: 3.7
Classifier: Programming Language :: Python :: 3.8
Classifier: Programming Language :: Python :: 3.9
Classifier: Programming Language :: Python :: 3.10
Classifier: Programming Language :: Python :: 3.11
Classifier: License :: OSI Approved :: Apache Software License
Classifier: Operating System :: OS Independent
Requires-Python: >=3.7
License-File: LICENSE
Requires-Dist: celery>=5.0
Requires-Dist: pymongo>=3.12
Provides-Extra: test
Requires-Dist: ephem; extra == "test"
Requires-Dist: mongomock; extra == "test"
Requires-Dist: pytest; extra == "test"
Dynamic: license-file
